CHANGES.txt
LICENSE.txt
MANIFEST.in
README.txt
setup.py
fatzebra/__init__.py
fatzebra/data.py
fatzebra/errors.py
fatzebra/gateway.py
fatzebra/version.py
fatzebra.egg-info/PKG-INFO
fatzebra.egg-info/SOURCES.txt
fatzebra.egg-info/dependency_links.txt
fatzebra.egg-info/requires.txt
fatzebra.egg-info/top_level.txt
test/test_gateway.py