Metadata-Version: 1.0
Name: fatzebra
Version: 0.0.4
Summary: Fat Zebra Python Library
Home-page: https://www.fatzebra.com.au/
Author: Fat Zebra
Author-email: support@fatzebra.com.au
License: UNKNOWN
Platform: UNKNOWN
